grepmx/__init__.py
grepmx/__main__.py
grepmx/grepmx.py
grepmx-1.0.0.dist-info/METADATA
grepmx-1.0.0.dist-info/RECORD
grepmx-1.0.0.dist-info/WHEEL
grepmx-1.0.0.dist-info/entry_points.txt
grepmx-1.0.0.dist-info/top_level.txt
